alpha_bpc/BPC.py
alpha_bpc/__init__.py
alpha_bpc/utils/__init__.py
alpha_bpc/utils/cks.py
alpha_bpc/utils/convolve_filts.py
alpha_bpc/utils/crs.py
alpha_bpc/utils/extract_filters.py
alpha_bpc/utils/load_fmnist.py
alpha_bpc/utils/rs.py
examples/__init__.py
examples/fmnist_bpc.py
examples/mnist_bpc.py
alpha_bpc-0.1.2.dist-info/AUTHORS.rst
alpha_bpc-0.1.2.dist-info/LICENSE
alpha_bpc-0.1.2.dist-info/METADATA
alpha_bpc-0.1.2.dist-info/WHEEL
alpha_bpc-0.1.2.dist-info/top_level.txt
alpha_bpc-0.1.2.dist-info/RECORD
